affectlog_feature_extractors/__init__.py
affectlog_feature_extractors/attribute_extractors.py
affectlog_feature_extractors/data/__init__.py
affectlog_feature_extractors/data/female-words.txt
affectlog_feature_extractors/data/male-words.txt
affectlog_feature_extractors/data/neutral-words.txt
affectlog_feature_extractors-0.2.1.dist-info/METADATA
affectlog_feature_extractors-0.2.1.dist-info/WHEEL
affectlog_feature_extractors-0.2.1.dist-info/top_level.txt
affectlog_feature_extractors-0.2.1.dist-info/RECORD
